joinboost/__init__.py
joinboost/aggregator.py
joinboost/app.py
joinboost/cjt.py
joinboost/d3graph.html
joinboost/executor.py
joinboost/joingraph.py
joinboost/preprocessor.py
joinboost/semiring.py
joinboost/static_files/dashboard.html
joinboost/static_files/.ipynb_checkpoints/dashboard-checkpoint.html
joinboost-0.0.1523.dist-info/LICENSE
joinboost-0.0.1523.dist-info/METADATA
joinboost-0.0.1523.dist-info/WHEEL
joinboost-0.0.1523.dist-info/top_level.txt
joinboost-0.0.1523.dist-info/RECORD
