Metadata-Version: 2.1
Name: joinboost
Version: 0.0.1523
Summary: JoinBoost: In-Database Tree-Models over Many Tables
License-File: LICENSE
